spotiv3/__init__.py
spotiv3/recaptcha.py
spotiv3-0.3.9.dist-info/METADATA
spotiv3-0.3.9.dist-info/WHEEL
spotiv3-0.3.9.dist-info/top_level.txt
spotiv3-0.3.9.dist-info/RECORD
