Metadata-Version: 2.1
Name: spotiv3
Version: 0.3.9
Summary: A Python module for bypassing reCAPTCHA v3
Home-page: https://github.com/yourusername/spotiv3
Author: Your Name
Author-email: your.email@example.com
Classifier: Programming Language :: Python :: 3
Classifier: License :: OSI Approved :: MIT License
Classifier: Operating System :: OS Independent
Requires-Dist: requests
